python_fang222/__init__.py
python_fang222/cli.py
python_fang222/example.py
python_fang222/python_fang222.py
python_fang222-0.3.0.dist-info/licenses/AUTHORS.rst
python_fang222-0.3.0.dist-info/licenses/LICENSE
python_fang222-0.3.0.dist-info/METADATA
python_fang222-0.3.0.dist-info/WHEEL
python_fang222-0.3.0.dist-info/top_level.txt
python_fang222-0.3.0.dist-info/RECORD
