Metadata-Version: 2.4
Name: python_fang222
Version: 0.3.0
Summary: Python Boilerplate contains all the boilerplate you need to create a Python package.
Author-email: fanghongjian <1107847724@qq.com>
Maintainer-email: fanghongjian <1107847724@qq.com>
License: MIT license
Project-URL: bugs, https://github.com/gunhe/python_fang222/issues
Project-URL: changelog, https://github.com/gunhe/python_fang222/blob/master/changelog.md
Project-URL: homepage, https://github.com/gunhe/python_fang222
License-File: LICENSE
License-File: AUTHORS.rst
Requires-Dist: typer
Provides-Extra: dev
Requires-Dist: coverage; extra == "dev"
Requires-Dist: mypy; extra == "dev"
Requires-Dist: pytest; extra == "dev"
Requires-Dist: ruff; extra == "dev"
Dynamic: license-file
